dissentty_vk/__init__.py
dissentty_vk/api.py
dissentty_vk/bot.py
dissentty_vk-0.3.dist-info/METADATA
dissentty_vk-0.3.dist-info/WHEEL
dissentty_vk-0.3.dist-info/entry_points.txt
dissentty_vk-0.3.dist-info/top_level.txt
dissentty_vk-0.3.dist-info/RECORD
